{
  "Ahmednagar Club": {
    "formatted_address": "",
    "formatted_phone_number": "",
    "geometry": {
      "location": {
        "lat": 0.0,
        "lng": 0.0
      }
    },
    "name": "Ahmednagar Club",
    "opening_hours": {
      "open_now": false,
      "periods": [],
      "weekday_text": []
    },
    "description": "",
    "photo_urls": [],
    "rating": 0.0,
    "reviews": [],
    "logo": "",
    "user_ratings_total": 0,
    "website": "ahmednagarclub.com",
    "activities": []
  },
  "Ahmednagar Gymkhana": {
    "formatted_address": "",
    "formatted_phone_number": "",
    "geometry": {
      "location": {
        "lat": 0.0,
        "lng": 0.0
      }
    },
    "name": "Ahmednagar Gymkhana",
    "opening_hours": {
      "open_now": false,
      "periods": [],
      "weekday_text": []
    },
    "description": "",
    "photo_urls": [],
    "rating": 0.0,
    "reviews": [],
    "logo": "",
    "user_ratings_total": 0,
    "website": "ahmednagargymkhana.com",
    "activities": []
  }
}