{
  "Cambodian Country Club": {
    "formatted_address": "",
    "formatted_phone_number": "",
    "geometry": {
      "location": {
        "lat": 0.0,
        "lng": 0.0
      }
    },
    "name": "Cambodian Country Club",
    "opening_hours": {
      "open_now": false,
      "periods": [],
      "weekday_text": []
    },
    "description": "",
    "photo_urls": [],
    "rating": 0.0,
    "reviews": [],
    "logo": "",
    "user_ratings_total": 0,
    "website": "",
    "activities": []
  },
  "Foreign Correspondents’ Club Phnom Penh": {
    "formatted_address": "",
    "formatted_phone_number": "",
    "geometry": {
      "location": {
        "lat": 0.0,
        "lng": 0.0
      }
    },
    "name": "Foreign Correspondents’ Club Phnom Penh",
    "opening_hours": {
      "open_now": false,
      "periods": [],
      "weekday_text": []
    },
    "description": "",
    "photo_urls": [],
    "rating": 0.0,
    "reviews": [],
    "logo": "",
    "user_ratings_total": 0,
    "website": "fcccollection.com/phnom-penh/",
    "activities": []
  },
  "Vault Club": {
    "formatted_address": "",
    "formatted_phone_number": "",
    "geometry": {
      "location": {
        "lat": 0.0,
        "lng": 0.0
      }
    },
    "name": "Vault Club",
    "opening_hours": {
      "open_now": false,
      "periods": [],
      "weekday_text": []
    },
    "description": "",
    "photo_urls": [],
    "rating": 0.0,
    "reviews": [],
    "logo": "",
    "user_ratings_total": 0,
    "website": "thevault-cambodia.com",
    "activities": []
  }
}