{
  "Seoul City Club": {
    "formatted_address": "",
    "formatted_phone_number": "",
    "geometry": {
      "location": {
        "lat": 0.0,
        "lng": 0.0
      }
    },
    "name": "Seoul City Club",
    "opening_hours": {
      "open_now": false,
      "periods": [],
      "weekday_text": []
    },
    "description": "",
    "photo_urls": [],
    "rating": 0.0,
    "reviews": [],
    "logo": "",
    "user_ratings_total": 0,
    "website": "seoulcityclub.co.kr",
    "activities": []
  },
  "Seoul Club": {
    "formatted_address": "208 Jangchoong-dong 2GA, Seoul, Korea",
    "formatted_phone_number": "822 2238 7666 , 82222343866",
    "geometry": {
      "location": {
        "lat": 0.0,
        "lng": 0.0
      }
    },
    "name": "Seoul Club",
    "opening_hours": {
      "open_now": false,
      "periods": [],
      "weekday_text": []
    },
    "description": "",
    "photo_urls": [],
    "rating": 0.0,
    "reviews": [],
    "logo": "",
    "user_ratings_total": 0,
    "website": "seoulclub.org",
    "activities": []
  },
  "The Seoul Club": {
    "formatted_address": "#86 Jangchungdan-ro, Jung-gu",
    "formatted_phone_number": "+82 2 2238 7666",
    "geometry": {
      "location": {
        "lat": 0.0,
        "lng": 0.0
      }
    },
    "name": "The Seoul Club",
    "opening_hours": {
      "open_now": false,
      "periods": [],
      "weekday_text": []
    },
    "description": "",
    "photo_urls": [],
    "rating": 0.0,
    "reviews": [],
    "logo": "",
    "user_ratings_total": 0,
    "website": "",
    "activities": [
      "tennis",
      "athletic",
      "swimming"
    ]
  }
}