{
  "Australasian Pioneers Club": {
    "formatted_address": "",
    "formatted_phone_number": "",
    "geometry": {
      "location": {
        "lat": 0.0,
        "lng": 0.0
      }
    },
    "name": "Australasian Pioneers Club",
    "opening_hours": {
      "open_now": false,
      "periods": [],
      "weekday_text": []
    },
    "description": "",
    "photo_urls": [],
    "rating": 0.0,
    "reviews": [],
    "logo": "",
    "user_ratings_total": 0,
    "website": "pioneersclub.com.au",
    "activities": []
  },
  "Australian Club Sydney": {
    "formatted_address": "",
    "formatted_phone_number": "(02) 9229 0400",
    "geometry": {
      "location": {
        "lat": 0.0,
        "lng": 0.0
      }
    },
    "name": "Australian Club Sydney",
    "opening_hours": {
      "open_now": false,
      "periods": [],
      "weekday_text": []
    },
    "description": "",
    "photo_urls": [],
    "rating": 0.0,
    "reviews": [],
    "logo": "",
    "user_ratings_total": 0,
    "website": "165macquariestreet.com.au",
    "activities": []
  },
  "City Tattersall’s Club": {
    "formatted_address": "194 - 204 Pitt Street",
    "formatted_phone_number": "+61 2 92679421",
    "geometry": {
      "location": {
        "lat": 0.0,
        "lng": 0.0
      }
    },
    "name": "City Tattersall’s Club",
    "opening_hours": {
      "open_now": false,
      "periods": [],
      "weekday_text": []
    },
    "description": "",
    "photo_urls": [],
    "rating": 0.0,
    "reviews": [],
    "logo": "",
    "user_ratings_total": 0,
    "website": "citytatts.com.au",
    "activities": [
      "athletic",
      "swimming"
    ]
  },
  "Club of United Business": {
    "formatted_address": "",
    "formatted_phone_number": "",
    "geometry": {
      "location": {
        "lat": 0.0,
        "lng": 0.0
      }
    },
    "name": "Club of United Business",
    "opening_hours": {
      "open_now": false,
      "periods": [],
      "weekday_text": []
    },
    "description": "",
    "photo_urls": [],
    "rating": 0.0,
    "reviews": [],
    "logo": "",
    "user_ratings_total": 0,
    "website": "cub.club",
    "activities": []
  },
  "CTA Business Club": {
    "formatted_address": "MCL Centre, Martin Place, Sydney, Australia, 2000 (Closed until June 2025)",
    "formatted_phone_number": "61 29232 7344 , 61292323207",
    "geometry": {
      "location": {
        "lat": 0.0,
        "lng": 0.0
      }
    },
    "name": "CTA Business Club",
    "opening_hours": {
      "open_now": false,
      "periods": [],
      "weekday_text": []
    },
    "description": "",
    "photo_urls": [],
    "rating": 0.0,
    "reviews": [],
    "logo": "",
    "user_ratings_total": 0,
    "website": "ctabusinessclub.com",
    "activities": []
  },
  "Queen’s Club Sydney": {
    "formatted_address": "",
    "formatted_phone_number": "",
    "geometry": {
      "location": {
        "lat": 0.0,
        "lng": 0.0
      }
    },
    "name": "Queen’s Club Sydney",
    "opening_hours": {
      "open_now": false,
      "periods": [],
      "weekday_text": []
    },
    "description": "",
    "photo_urls": [],
    "rating": 0.0,
    "reviews": [],
    "logo": "",
    "user_ratings_total": 0,
    "website": "queensclub.com.au",
    "activities": []
  },
  "Royal Automobile Club of Australia": {
    "formatted_address": "89 Macquarie Street, Sydney, Australia, NSW 2000",
    "formatted_phone_number": "61 28273 2300 , 61282732301",
    "geometry": {
      "location": {
        "lat": 0.0,
        "lng": 0.0
      }
    },
    "name": "Royal Automobile Club of Australia",
    "opening_hours": {
      "open_now": false,
      "periods": [],
      "weekday_text": []
    },
    "description": "",
    "photo_urls": [],
    "rating": 0.0,
    "reviews": [],
    "logo": "",
    "user_ratings_total": 0,
    "website": "raca.com.au",
    "activities": []
  },
  "Royal Exchange of Sydney": {
    "formatted_address": "",
    "formatted_phone_number": "",
    "geometry": {
      "location": {
        "lat": 0.0,
        "lng": 0.0
      }
    },
    "name": "Royal Exchange of Sydney",
    "opening_hours": {
      "open_now": false,
      "periods": [],
      "weekday_text": []
    },
    "description": "",
    "photo_urls": [],
    "rating": 0.0,
    "reviews": [],
    "logo": "",
    "user_ratings_total": 0,
    "website": "royalexchange.com.au",
    "activities": []
  },
  "Union, University & Schools Club": {
    "formatted_address": "",
    "formatted_phone_number": "",
    "geometry": {
      "location": {
        "lat": 0.0,
        "lng": 0.0
      }
    },
    "name": "Union, University & Schools Club",
    "opening_hours": {
      "open_now": false,
      "periods": [],
      "weekday_text": []
    },
    "description": "",
    "photo_urls": [],
    "rating": 0.0,
    "reviews": [],
    "logo": "",
    "user_ratings_total": 0,
    "website": "uusc.com.au",
    "activities": []
  },
  "Women’s Club": {
    "formatted_address": "",
    "formatted_phone_number": "",
    "geometry": {
      "location": {
        "lat": 0.0,
        "lng": 0.0
      }
    },
    "name": "Women’s Club",
    "opening_hours": {
      "open_now": false,
      "periods": [],
      "weekday_text": []
    },
    "description": "",
    "photo_urls": [],
    "rating": 0.0,
    "reviews": [],
    "logo": "",
    "user_ratings_total": 0,
    "website": "thewomensclub.com.au",
    "activities": []
  }
}